{
    "id": "string",
    "version": "string",
    "name": "string",
    "type": "[ann-workflow]",
    "contract": "path-to-dtos-version-controact-as-string",
    "topology": {
        "layers": [
            {
                "layer": "0",
                "ann": [
                    "ann-id0",
                    "ann-id1"
                ],
                "wiring": null,
                "output": [
                    "ann-id0::output-name0"
                ]
            },
            {
                "layer": "1",
                "ann": [
                    "ann-id0",
                    "ann-id1",
                    "ann-id2"
                ],
                "wiring": [
                    "ann-id0::output-name0---ann-id0::input-name0",
                    "ann-id0::output-name0---ann-id1::input-name1",
                    "ann-id1::output-name1---ann-id2::input-name2"
                ],
                "output": null
            },
            {
                "layer": "2",
                "ann": [
                    "ann-id0"
                ],
                "wiring": [
                    "ann-id1::output-name1---ann-id0::input-name1",
                    "ann-id1::output-name1---ann-id0::input-name2",
                    "ann-id2::output-name2---ann-id0::input-name3"
                ],
                "output": [
                    "ann-id::output-name0"
                ]
            }
        ]
    }
}